SimpleTALSix-6.2.1.dist-info/DESCRIPTION.rst
SimpleTALSix-6.2.1.dist-info/METADATA
SimpleTALSix-6.2.1.dist-info/RECORD
SimpleTALSix-6.2.1.dist-info/WHEEL
SimpleTALSix-6.2.1.dist-info/metadata.json
SimpleTALSix-6.2.1.dist-info/top_level.txt
simpletal/__init__.py
simpletal/simpleTAL.py
simpletal/simpleTALConstants.py
simpletal/simpleTALES.py
simpletal/simpleTALUtils.py
