Metadata-Version: 2.0
Name: SimpleTALSix
Version: 6.2.1
Summary: Stand alone Python implementation of the TAL, TALES and METAL specifications used in Zope to power HTML and XML templates.
Home-page: https://github.com/janbrohl/SimpleTAL
Author: Jan Brohl
Author-email: janbrohl@t-online.de
License: BSD-3-Clause
Platform: UNKNOWN
Classifier: Intended Audience :: Developers
Classifier: Development Status :: 4 - Beta
Classifier: License :: OSI Approved :: BSD License
Classifier: Operating System :: OS Independent
Classifier: Programming Language :: Python
Classifier: Programming Language :: Python :: 2
Classifier: Programming Language :: Python :: 2.7
Classifier: Programming Language :: Python :: 3
Classifier: Programming Language :: Python :: 3.2
Classifier: Programming Language :: Python :: 3.3
Classifier: Programming Language :: Python :: 3.4
Classifier: Programming Language :: Python :: 3.5
Classifier: Programming Language :: Python :: 3.6
Provides: SimpleTAL
Requires-Python: ~=2.7,~=3.2
